heimdall/__init__.py
heimdall/core.py
heimdall/utils.py
heimdall/visualization.py
heimdall_graph-0.1.0.dist-info/licenses/LICENSE
heimdall_graph-0.1.0.dist-info/METADATA
heimdall_graph-0.1.0.dist-info/WHEEL
heimdall_graph-0.1.0.dist-info/top_level.txt
heimdall_graph-0.1.0.dist-info/RECORD
