Metadata-Version: 2.4
Name: heimdall-graph
Version: 0.1.0
Summary: A package for community detection using SVD.
License: MIT License
Project-URL: Homepage, https://github.com/romulorcruz/Heimdall
Project-URL: Bug Tracker, https://github.com/romulorcruz/Heimdallissues
Classifier: Programming Language :: Python :: 3
Classifier: License :: OSI Approved :: MIT License
Classifier: Operating System :: OS Independent
Classifier: Intended Audience :: Science/Research
Classifier: Topic :: Scientific/Engineering :: Information Analysis
Requires-Python: >=3.8
License-File: LICENSE
Requires-Dist: numpy
Requires-Dist: matplotlib
Dynamic: license-file
